patroni/__init__.py
patroni/__main__.py
patroni/api.py
patroni/async_executor.py
patroni/collections.py
patroni/config.py
patroni/config_generator.py
patroni/ctl.py
patroni/daemon.py
patroni/dynamic_loader.py
patroni/exceptions.py
patroni/file_perm.py
patroni/global_config.py
patroni/ha.py
patroni/log.py
patroni/psycopg.py
patroni/quorum.py
patroni/raft_controller.py
patroni/request.py
patroni/tags.py
patroni/utils.py
patroni/validator.py
patroni/version.py
patroni/dcs/__init__.py
patroni/dcs/consul.py
patroni/dcs/etcd.py
patroni/dcs/etcd3.py
patroni/dcs/exhibitor.py
patroni/dcs/kubernetes.py
patroni/dcs/raft.py
patroni/dcs/zookeeper.py
patroni/postgresql/__init__.py
patroni/postgresql/bootstrap.py
patroni/postgresql/callback_executor.py
patroni/postgresql/cancellable.py
patroni/postgresql/config.py
patroni/postgresql/connection.py
patroni/postgresql/misc.py
patroni/postgresql/postmaster.py
patroni/postgresql/rewind.py
patroni/postgresql/slots.py
patroni/postgresql/sync.py
patroni/postgresql/validator.py
patroni/postgresql/available_parameters/0_postgres.yml
patroni/postgresql/available_parameters/__init__.py
patroni/postgresql/mpp/__init__.py
patroni/postgresql/mpp/citus.py
patroni/scripts/__init__.py
patroni/scripts/aws.py
patroni/scripts/wale_restore.py
patroni/scripts/barman/__init__.py
patroni/scripts/barman/cli.py
patroni/scripts/barman/config_switch.py
patroni/scripts/barman/recover.py
patroni/scripts/barman/utils.py
patroni/watchdog/__init__.py
patroni/watchdog/base.py
patroni/watchdog/linux.py
patroni-4.1.0.dist-info/licenses/LICENSE
patroni-4.1.0.dist-info/METADATA
patroni-4.1.0.dist-info/WHEEL
patroni-4.1.0.dist-info/entry_points.txt
patroni-4.1.0.dist-info/top_level.txt
patroni-4.1.0.dist-info/RECORD
