Metadata-Version: 2.4
Name: patroni
Version: 4.1.0
Summary: PostgreSQL High-Available orchestrator and CLI
Home-page: https://github.com/patroni/patroni
Author: Alexander Kukushkin, Polina Bungina
Author-email: akukushkin@microsoft.com, polina.bungina@zalando.de
License: The MIT License
Keywords: etcd governor patroni postgresql postgres ha haproxy confd zookeeper exhibitor consul streaming replication kubernetes k8s
Classifier: Development Status :: 5 - Production/Stable
Classifier: Environment :: Console
Classifier: Intended Audience :: Developers
Classifier: Intended Audience :: System Administrators
Classifier: Operating System :: MacOS
Classifier: Operating System :: POSIX :: Linux
Classifier: Operating System :: POSIX :: BSD :: FreeBSD
Classifier: Operating System :: Microsoft :: Windows
Classifier: Programming Language :: Python
Classifier: Programming Language :: Python :: 3
Classifier: Programming Language :: Python :: 3.6
Classifier: Programming Language :: Python :: 3.7
Classifier: Programming Language :: Python :: 3.8
Classifier: Programming Language :: Python :: 3.9
Classifier: Programming Language :: Python :: 3.10
Classifier: Programming Language :: Python :: 3.11
Classifier: Programming Language :: Python :: 3.12
Classifier: Programming Language :: Python :: 3.13
Classifier: Programming Language :: Python :: Implementation :: CPython
License-File: LICENSE
Requires-Dist: urllib3!=1.21,>=1.19.1
Requires-Dist: PyYAML
Requires-Dist: py-consul<1.6.0,>=1.1.1; python_version > "3.6" and python_version < "3.9"
Requires-Dist: py-consul>=1.1.1; python_version >= "3.9"
Requires-Dist: click>=5.0
Requires-Dist: prettytable>=0.7
Requires-Dist: python-dateutil
Requires-Dist: psutil>=2.0.0
Requires-Dist: ydiff!=1.4.0,!=1.4.1,<1.5,>=1.2.0
Provides-Extra: aws
Requires-Dist: boto3; extra == "aws"
Provides-Extra: etcd
Requires-Dist: python-etcd<0.5,>=0.4.3; extra == "etcd"
Provides-Extra: etcd3
Requires-Dist: python-etcd<0.5,>=0.4.3; extra == "etcd3"
Provides-Extra: consul
Requires-Dist: py-consul<1.5.4,>=1.1.1; python_version == "3.6" and extra == "consul"
Provides-Extra: exhibitor
Requires-Dist: kazoo>=1.3.1; extra == "exhibitor"
Provides-Extra: zookeeper
Requires-Dist: kazoo>=1.3.1; extra == "zookeeper"
Provides-Extra: systemd
Requires-Dist: systemd-python; extra == "systemd"
Provides-Extra: kubernetes
Provides-Extra: raft
Requires-Dist: pysyncobj>=0.3.8; extra == "raft"
Requires-Dist: cryptography>=1.4; extra == "raft"
Provides-Extra: jsonlogger
Requires-Dist: python-json-logger>=2.0.2; extra == "jsonlogger"
Provides-Extra: all
Requires-Dist: pysyncobj>=0.3.8; extra == "all"
Requires-Dist: py-consul<1.5.4,>=1.1.1; python_version == "3.6" and extra == "all"
Requires-Dist: cryptography>=1.4; extra == "all"
Requires-Dist: boto3; extra == "all"
Requires-Dist: kazoo>=1.3.1; extra == "all"
Requires-Dist: python-json-logger>=2.0.2; extra == "all"
Requires-Dist: python-etcd<0.5,>=0.4.3; extra == "all"
Requires-Dist: systemd-python; extra == "all"
Provides-Extra: psycopg2
Requires-Dist: psycopg2>=2.5.4; extra == "psycopg2"
Provides-Extra: psycopg2-binary
Requires-Dist: psycopg2-binary; extra == "psycopg2-binary"
Provides-Extra: psycopg3
Requires-Dist: psycopg[binary]>=3.0.0; extra == "psycopg3"
Dynamic: author
Dynamic: author-email
Dynamic: classifier
Dynamic: description
Dynamic: home-page
Dynamic: keywords
Dynamic: license
Dynamic: license-file
Dynamic: provides-extra
Dynamic: requires-dist
Dynamic: summary
